jupyterlab_promptclose/__init__.py
jupyterlab_promptclose/_version.py
jupyterlab_promptclose/labextension/package.json
jupyterlab_promptclose/labextension/static/568.74953320569c79a795c7.js
jupyterlab_promptclose/labextension/static/remoteEntry.09b11b504bb577c35e7e.js
jupyterlab_promptclose/labextension/static/style.js
jupyterlab_promptclose-0.1.0.data/data/share/jupyter/labextensions/@manics/jupyterlab-promptclose/install.json
jupyterlab_promptclose-0.1.0.data/data/share/jupyter/labextensions/@manics/jupyterlab-promptclose/package.json
jupyterlab_promptclose-0.1.0.data/data/share/jupyter/labextensions/@manics/jupyterlab-promptclose/static/568.74953320569c79a795c7.js
jupyterlab_promptclose-0.1.0.data/data/share/jupyter/labextensions/@manics/jupyterlab-promptclose/static/remoteEntry.09b11b504bb577c35e7e.js
jupyterlab_promptclose-0.1.0.data/data/share/jupyter/labextensions/@manics/jupyterlab-promptclose/static/style.js
jupyterlab_promptclose-0.1.0.dist-info/LICENSE
jupyterlab_promptclose-0.1.0.dist-info/METADATA
jupyterlab_promptclose-0.1.0.dist-info/WHEEL
jupyterlab_promptclose-0.1.0.dist-info/top_level.txt
jupyterlab_promptclose-0.1.0.dist-info/RECORD
